django_grouper/__init__.py
django_grouper/apps.py
django_grouper/templates/django_grouper/group.html
django_grouper/templates/django_grouper/grouper.html
django_grouper/urls.py
django_grouper/utils.py
django_grouper/views.py
django_grouper-0.2.0.dist-info/METADATA
django_grouper-0.2.0.dist-info/WHEEL
django_grouper-0.2.0.dist-info/RECORD
