Metadata-Version: 2.1
Name: django-grouper
Version: 0.2.0
Summary: 
Author: Birger Schacht
Requires-Python: >=3.10,<4.0
Classifier: Programming Language :: Python :: 3
Classifier: Programming Language :: Python :: 3.10
Classifier: Programming Language :: Python :: 3.11
Classifier: Programming Language :: Python :: 3.12
Requires-Dist: django (>=3)
Requires-Dist: pandas (>=2.2.2,<3.0.0)
Requires-Dist: scikit-learn (>=1.5.0,<2.0.0)
Requires-Dist: sparse-dot-topn (>=1.1.1,<2.0.0)
